vulncheck_sdk/__init__.py
vulncheck_sdk/api_client.py
vulncheck_sdk/api_response.py
vulncheck_sdk/configuration.py
vulncheck_sdk/exceptions.py
vulncheck_sdk/py.typed
vulncheck_sdk/rest.py
vulncheck_sdk/api/__init__.py
vulncheck_sdk/api/endpoints_api.py
vulncheck_sdk/api/indices_api.py
vulncheck_sdk/models/__init__.py
vulncheck_sdk/models/advisory_a10.py
vulncheck_sdk/models/advisory_abb_advisory.py
vulncheck_sdk/models/advisory_abbott.py
vulncheck_sdk/models/advisory_absolute.py
vulncheck_sdk/models/advisory_acknowledgement.py
vulncheck_sdk/models/advisory_acronis.py
vulncheck_sdk/models/advisory_adobe_advisory.py
vulncheck_sdk/models/advisory_adobe_affected.py
vulncheck_sdk/models/advisory_adobe_cve.py
vulncheck_sdk/models/advisory_adobe_solution.py
vulncheck_sdk/models/advisory_adp.py
vulncheck_sdk/models/advisory_adp_container.py
vulncheck_sdk/models/advisory_advantech.py
vulncheck_sdk/models/advisory_advisory.py
vulncheck_sdk/models/advisory_advisory_details.py
vulncheck_sdk/models/advisory_advisory_record.py
vulncheck_sdk/models/advisory_affected.py
vulncheck_sdk/models/advisory_affected_chrome.py
vulncheck_sdk/models/advisory_affected_debian_package.py
vulncheck_sdk/models/advisory_affected_debian_release.py
vulncheck_sdk/models/advisory_affected_debian_repository.py
vulncheck_sdk/models/advisory_affected_file.py
vulncheck_sdk/models/advisory_affected_product.py
vulncheck_sdk/models/advisory_affected_rel.py
vulncheck_sdk/models/advisory_affected_ubuntu_package.py
vulncheck_sdk/models/advisory_aix.py
vulncheck_sdk/models/advisory_aleph_research.py
vulncheck_sdk/models/advisory_alibaba.py
vulncheck_sdk/models/advisory_alma_date.py
vulncheck_sdk/models/advisory_alma_linux_update.py
vulncheck_sdk/models/advisory_alma_object_id.py
vulncheck_sdk/models/advisory_alma_package.py
vulncheck_sdk/models/advisory_alma_package_list.py
vulncheck_sdk/models/advisory_alma_reference.py
vulncheck_sdk/models/advisory_alpine_linux_sec_db.py
vulncheck_sdk-0.0.31.dist-info/licenses/LICENSE
vulncheck_sdk-0.0.31.dist-info/METADATA
vulncheck_sdk-0.0.31.dist-info/WHEEL
vulncheck_sdk-0.0.31.dist-info/top_level.txt
vulncheck_sdk-0.0.31.dist-info/RECORD
