Metadata-Version: 2.4
Name: vulncheck_sdk
Version: 0.0.31
Summary: VulnCheck API
Home-page: https://github.com/vulncheck-oss/sdk-python/tree/main
Author: VulnCheck API Support
Author-email: VulnCheck API Support <support@vulncheck.com>
License-Expression: Apache-2.0
Project-URL: Repository, https://github.com/vulncheck-oss/sdk-python
Keywords: OpenAPI,OpenAPI-Generator,VulnCheck API
Requires-Python: >=3.9
License-File: LICENSE
Requires-Dist: urllib3<3.0.0,>=2.1.0
Requires-Dist: python-dateutil>=2.8.2
Requires-Dist: pydantic>=2
Requires-Dist: typing-extensions>=4.7.1
Dynamic: author
Dynamic: home-page
Dynamic: license-file
